jetblack_options/__init__.py
jetblack_options/distributions.py
jetblack_options/implied_volatility.py
jetblack_options/american/__init__.py
jetblack_options/american/barone_adesi_whaley.py
jetblack_options/american/bjerksund_stensland_1993.py
jetblack_options/american/bjerksund_stensland_2002.py
jetblack_options/european/__init__.py
jetblack_options/european/black_76.py
jetblack_options/european/black_scholes_73.py
jetblack_options/european/black_scholes_merton.py
jetblack_options/european/garman_kolhagen.py
jetblack_options/european/generalised_black_scholes.py
jetblack_options/numeric_greeks/__init__.py
jetblack_options/numeric_greeks/with_carry.py
jetblack_options/numeric_greeks/with_dividend_yield.py
jetblack_options/numeric_greeks/without_carry.py
jetblack_options/trees/__init__.py
jetblack_options/trees/cox_ross_rubinstein.py
jetblack_options/trees/european_binomial.py
jetblack_options/trees/jarrow_rudd.py
jetblack_options/trees/leisen_reimer.py
jetblack_options/trees/trinomial.py
jetblack_options/variance/__init__.py
jetblack_options/variance/black_scholes.py
jetblack_options-1.0.0.dist-info/METADATA
jetblack_options-1.0.0.dist-info/WHEEL
jetblack_options-1.0.0.dist-info/top_level.txt
jetblack_options-1.0.0.dist-info/RECORD
