Metadata-Version: 2.1
Name: jetblack-options
Version: 1.0.0
Summary: Reference implementations for option pricing formula
Author-email: Rob Blackbourn <rob.blackbourn@gmail.com>
Project-URL: Homepage, https://github.com/rob-blackbourn/jetblack-options
Project-URL: Issues, https://github.com/rob-blackbourn/jetblack-options/issues
Classifier: Programming Language :: Python :: 3
Classifier: License :: OSI Approved :: MIT License
Classifier: Operating System :: OS Independent
Requires-Python: >=3.8
